pylibjpeg/__init__.py
pylibjpeg/_version.py
pylibjpeg/utils.py
pylibjpeg/pydicom/__init__.py
pylibjpeg/pydicom/utils.py
pylibjpeg/tests/__init__.py
pylibjpeg/tests/test_decode.py
pylibjpeg/tests/test_decode_pydicom.py
pylibjpeg/tests/test_encode.py
pylibjpeg/tests/test_encode_pydicom.py
pylibjpeg/tools/__init__.py
pylibjpeg/tools/jpegio.py
pylibjpeg/tools/utils.py
pylibjpeg/tools/s10918/__init__.py
pylibjpeg/tools/s10918/_markers.py
pylibjpeg/tools/s10918/_parsers.py
pylibjpeg/tools/s10918/_printers.py
pylibjpeg/tools/s10918/io.py
pylibjpeg/tools/s10918/rep.py
pylibjpeg/tools/tests/__init__.py
pylibjpeg/tools/tests/test_utils.py
pylibjpeg-1.4.0.dist-info/LICENCE.txt
pylibjpeg-1.4.0.dist-info/METADATA
pylibjpeg-1.4.0.dist-info/WHEEL
pylibjpeg-1.4.0.dist-info/top_level.txt
pylibjpeg-1.4.0.dist-info/RECORD
