Metadata-Version: 2.1
Name: pylibjpeg
Version: 1.4.0
Summary: A Python framework for decoding JPEG and decoding/encoding DICOM RLE data, with a focus on supporting pydicom
Home-page: https://github.com/pydicom/pylibjpeg
Author: scaramallion
Author-email: scaramallion@users.noreply.github.com
License: MIT
Keywords: dcm dicom pydicom python imaging jpg jpeg jpg-ls jpeg-ls jpeg2k jpeg2000 rle libjpeg pylibjpeg
Platform: UNKNOWN
Classifier: License :: OSI Approved :: MIT License
Classifier: Intended Audience :: Developers
Classifier: Intended Audience :: Healthcare Industry
Classifier: Intended Audience :: Science/Research
Classifier: Development Status :: 5 - Production/Stable
Classifier: Natural Language :: English
Classifier: Programming Language :: Python :: 3.7
Classifier: Programming Language :: Python :: 3.8
Classifier: Programming Language :: Python :: 3.9
Classifier: Programming Language :: Python :: 3.10
Classifier: Operating System :: OS Independent
Classifier: Topic :: Scientific/Engineering :: Medical Science Apps.
Classifier: Topic :: Software Development :: Libraries
Requires-Python: >=3.7
Provides-Extra: rle
Provides-Extra: openjpeg
Provides-Extra: libjpeg
Provides-Extra: all
License-File: LICENCE.txt
